third_party/__init__.py
third_party/pyfixmsg/LICENSE.md
third_party/pyfixmsg/METADATA
third_party/pyfixmsg/__init__.py
third_party/pyfixmsg/codecs/__init__.py
third_party/pyfixmsg/codecs/stringfix.py
third_party/pyfixmsg/exception/FixSchemaNotDefinedError.py
third_party/pyfixmsg/exception/__init__.py
third_party/pyfixmsg/fixmessage.py
third_party/pyfixmsg/parser.py
third_party/pyfixmsg/reference.py
third_party/pyfixmsg/util.py
third_party/sbedecoder/LICENSE.txt
third_party/sbedecoder/METADATA
third_party/sbedecoder/__init__.py
third_party/sbedecoder/message.py
third_party/sbedecoder/parser.py
third_party/sbedecoder/schema.py
third_party/sbedecoder/typemap.py
transcoder/.gitignore
transcoder/Transcoder.py
transcoder/__init__.py
transcoder/main.py
transcoder/message/DatacastField.py
transcoder/message/DatacastGroup.py
transcoder/message/DatacastParser.py
transcoder/message/DatacastSchema.py
transcoder/message/ErrorWriter.py
transcoder/message/MessageUtil.py
transcoder/message/NoParser.py
transcoder/message/ParsedMessage.py
transcoder/message/__init__.py
transcoder/message/exception/MessageParserNotDefinedError.py
transcoder/message/exception/ParserFunctionNotDefinedError.py
transcoder/message/exception/__init__.py
transcoder/message/factory/CmeMessageFactory.py
transcoder/message/factory/ITCHMessageFactory.py
transcoder/message/factory/MDPMessageFactory.py
transcoder/message/factory/MemxMessageFactory.py
transcoder/message/factory/MessageFactory.py
transcoder/message/factory/__init__.py
transcoder/message/factory/exception/FactoryNotFoundError.py
transcoder/message/factory/exception/TemplateSchemaNotDefinedError.py
transcoder/message/factory/exception/__init__.py
transcoder/message/handler/CmeBinaryPacketHandler.py
transcoder/message/handler/FilterHandler.py
transcoder/message/handler/MessageHandler.py
transcoder/message/handler/MessageHandlerFloatField.py
transcoder/message/handler/MessageHandlerIntField.py
transcoder/message/handler/MessageHandlerStringField.py
market_data_transcoder-1.0.8.dist-info/LICENSE
market_data_transcoder-1.0.8.dist-info/METADATA
market_data_transcoder-1.0.8.dist-info/WHEEL
market_data_transcoder-1.0.8.dist-info/entry_points.txt
market_data_transcoder-1.0.8.dist-info/RECORD
