Metadata-Version: 2.3
Name: market-data-transcoder
Version: 1.0.8
Summary: The Datacast transcoder is a schema-driven, message-oriented utility to simplify the lossless ingestion of common high-performance electronic trading data formats to Google Cloud.
License: Apache-2.0
Keywords: bigquery,devops,json,automation,schema,trading,avro,binary,transcoding,pubsub,fix,fixprotocol,google-cloud-platform,itch,sbe,simple-binary-encoding,exchanges,marketdata,binaryencoding
Author: Google Cloud FSI Solutions
Requires-Python: >=3.11,<4.0
Classifier: Intended Audience :: Developers
Classifier: Intended Audience :: Financial and Insurance Industry
Classifier: License :: OSI Approved :: Apache Software License
Classifier: Operating System :: OS Independent
Classifier: Programming Language :: Python :: 3
Classifier: Programming Language :: Python :: 3.11
Classifier: Programming Language :: Python :: 3.12
Classifier: Programming Language :: Python :: 3.13
Requires-Dist: avro (==1.12.1)
Requires-Dist: dpkt (==1.9.8)
Requires-Dist: fastavro (==1.12.1)
Requires-Dist: google-cloud-bigquery (==3.40.0)
Requires-Dist: google-cloud-pubsub (==2.34.0)
Requires-Dist: lxml (==6.0.2)
Requires-Dist: numpy (==2.4.1)
Requires-Dist: pyyaml (==6.0.3)
Requires-Dist: six (>=1.17.0)
Project-URL: Documentation, https://github.com/GoogleCloudPlatform/market-data-transcoder
Project-URL: Homepage, https://github.com/GoogleCloudPlatform/market-data-transcoder
Project-URL: Repository, https://github.com/GoogleCloudPlatform/market-data-transcoder
